{"btc_idr": 1390034000.0, "ada_idr": 4610.0, "aura_idr": 360.0, "bnb_idr": 11801500.0, "bnkr_idr": 9.126, "degen_idr": 16.0, "doge_idr": 1993.0, "eth_idr": 39134000.0, "fartcoin_idr": 3539.0, "hype_idr": 780000.0, "myx_idr": 3513.0, "islm_idr": 210.0, "jellyjelly_idr": 1142.123, "paxg_idr": 80299991.0, "pengu_idr": 155.519, "pepe_idr": 0.06892, "pippin_idr": 420.531, "ponke_idr": 692.0, "siren_idr": 9167.0, "sol_idr": 1569997.0, "sui_idr": 19434.0, "sundog_idr": 112.0, "trollsol_idr": 2068.001, "whitewhale_idr": 109.0, "xaut_idr": 79984087.0, "xrp_idr": 25264.0, "zerebro_idr": 500.0}