{"btc_idr": 1307071000.0, "bnb_idr": 11971993.0, "bnkr_idr": 11.27, "dgb_idr": 73.0, "dodo_idr": 804.0, "doge_idr": 1791.0, "eden_idr": 927.0, "eth_idr": 35899000.0, "ever_idr": 74.0, "fartcoin_idr": 2853.0, "hbar_idr": 1745.0, "hype_idr": 1188238.0, "spaceid_idr": 747.0, "inj_idr": 117186.0, "islm_idr": 168.0, "jellyjelly_idr": 1000.942, "nfp_idr": 256.0, "nom_idr": 38.185, "pepe_idr": 0.06084, "pippin_idr": 341.351, "portal_idr": 213.0, "sol_idr": 1463967.0, "sui_idr": 16110.0, "syn_idr": 1200.0, "tlm_idr": 104.0, "trollsol_idr": 1559.004, "xlm_idr": 4387.0, "xrp_idr": 23850.0, "zerebro_idr": 393.0}