{"btc_idr": 1161083000.0, "ada_idr": 3625.0, "avnt_idr": 2418.0, "bnb_idr": 11267981.0, "bp_idr": 5035.0, "dexe_idr": 318199.0, "dodo_idr": 1488.0, "doge_idr": 1648.0, "eden_idr": 877.0, "ena_idr": 2044.0, "eth_idr": 32827000.0, "ever_idr": 107.0, "fartcoin_idr": 2584.0, "humanity_idr": 10539.0, "hype_idr": 1341976.0, "myx_idr": 5256.0, "jellyjelly_idr": 1087.323, "near_idr": 51482.0, "ondo_idr": 7514.0, "pepe_idr": 0.056368, "pippin_idr": 299.416, "portal_idr": 356.0, "sapien_idr": 1630.0, "skyai_idr": 3020.0, "sol_idr": 1296141.0, "sto_idr": 1325.0, "syn_idr": 2268.0, "trollsol_idr": 1416.999, "ub_idr": 1940.0, "wld_idr": 9880.0, "whitewhale_idr": 81.0, "xlm_idr": 3805.0, "xrp_idr": 21671.0, "zen_idr": 100211.0, "zerebro_idr": 452.0, "zora_idr": 197.809}