{"btc_idr": 1407938000.0, "aih_idr": 728400.0, "aura_idr": 590.0, "bio_idr": 922.0, "bnb_idr": 11369172.0, "brett_idr": 172.0, "doge_idr": 1897.0, "eth_idr": 40663000.0, "fartcoin_idr": 4445.0, "giga_idr": 67.0, "hype_idr": 752354.0, "islm_idr": 227.0, "kdag_idr": 18.0, "moodeng_idr": 1158.0, "ondo_idr": 7172.0, "pengu_idr": 185.284, "pepe_idr": 0.074803, "pippin_idr": 457.538, "ponke_idr": 722.0, "rfc_idr": 15.994, "rss3_idr": 216.0, "sahara_idr": 650.0, "sol_idr": 1642996.0, "solayer_idr": 2126.0, "sui_idr": 22175.0, "sundog_idr": 111.0, "ton_idr": 41700.0, "trollsol_idr": 1679.001, "whitewhale_idr": 123.0, "xrp_idr": 25618.0, "zerebro_idr": 857.0, "zkj_idr": 219.0}