{"btc_idr": 1141999000.0, "ada_idr": 3281.0, "beat_idr": 43524.0, "bnb_idr": 10422145.0, "doge_idr": 1375.0, "edena_idr": 373.0, "ern_idr": 7023.0, "eth_idr": 32056000.0, "fartcoin_idr": 2982.0, "hmstr_idr": 6.427, "hype_idr": 1277610.0, "myx_idr": 1525.0, "magic_idr": 795.0, "nfp_idr": 110.0, "pepe_idr": 0.049106, "pippin_idr": 342.427, "siren_idr": 629.0, "skyai_idr": 961.0, "sol_idr": 1467648.0, "syn_idr": 6666.0, "taiko_idr": 8304.0, "tlm_idr": 63.0, "vanry_idr": 133.0, "wbtc_idr": 1182899998.0, "xrp_idr": 20648.0, "zerebro_idr": 708.0}