{"btc_idr": 1397474000.0, "aura_idr": 538.0, "buildon_idr": 6081.0, "bio_idr": 950.0, "bnb_idr": 11300000.0, "brett_idr": 168.0, "doge_idr": 1879.0, "eth_idr": 40284000.0, "fartcoin_idr": 4407.0, "giga_idr": 64.0, "myx_idr": 4627.0, "islm_idr": 225.0, "kdag_idr": 18.0, "moodeng_idr": 1129.0, "mtl_idr": 29798.0, "ondo_idr": 7013.0, "payai_idr": 154.8, "pengu_idr": 183.223, "pepe_idr": 0.073879, "pippin_idr": 436.001, "ponke_idr": 634.0, "rfc_idr": 13.635, "rss3_idr": 222.0, "sahara_idr": 600.0, "sol_idr": 1628872.0, "solayer_idr": 2411.0, "sui_idr": 19451.0, "sundog_idr": 124.0, "ton_idr": 41751.0, "trollsol_idr": 1555.0, "whitewhale_idr": 132.0, "xaut_idr": 81437903.0, "xrp_idr": 24702.0, "zerebro_idr": 882.0, "zkj_idr": 216.0}