{"btc_idr": 1130000000.0, "ada_idr": 3208.0, "buildon_idr": 2982.0, "beat_idr": 47467.0, "doge_idr": 1341.0, "edena_idr": 353.0, "ern_idr": 6552.0, "eth_idr": 31722000.0, "fartcoin_idr": 2877.0, "hmstr_idr": 5.476, "hype_idr": 1268764.0, "myx_idr": 1449.0, "magic_idr": 777.0, "nfp_idr": 107.0, "pippin_idr": 331.537, "skyai_idr": 792.0, "sol_idr": 1459032.0, "syn_idr": 6566.0, "tlm_idr": 63.0, "vanry_idr": 145.0, "voxel_idr": 67.0, "wbtc_idr": 1155782687.0, "xrp_idr": 20171.0, "zerebro_idr": 718.0}