{"btc_idr": 1344596000.0, "aztec_idr": 451.662, "beat_idr": 21890.0, "cast_idr": 3899999.0, "cjl_idr": 296.0, "col_idr": 2424.0, "dfg_idr": 28274.0, "dlc_idr": 269.0, "doge_idr": 1806.0, "eden_idr": 1180.0, "edena_idr": 1032.0, "eth_idr": 36947000.0, "fartcoin_idr": 3079.0, "h2o_idr": 9.0, "hifi_idr": 86.0, "hype_idr": 1115855.0, "jellyjelly_idr": 1011.94, "mrs_idr": 12118.0, "near_idr": 43657.0, "pepe_idr": 0.062488, "plpa_idr": 99.34, "pha_idr": 856.0, "pippin_idr": 373.694, "pond_idr": 94.305, "req_idr": 1467.0, "skyai_idr": 3955.0, "sn_idr": 2020.0, "sol_idr": 1484032.0, "sui_idr": 17729.0, "trollsol_idr": 1482.072, "ub_idr": 3765.0, "ucjl_idr": 20196.0, "uw3s_idr": 6.0, "w3s2_idr": 5116.0, "wld_idr": 6288.0, "whitewhale_idr": 105.0, "xrp_idr": 23627.0, "zerebro_idr": 391.0, "zkj_idr": 171.0}